{
  "export_info": {
    "mlflow_version": "1.26.0",
    "mlflow_tracking_uri": "databricks",
    "export_time": "2022-06-12 03:14:47"
  },
  "info": {
    "run_uuid": "f2e3f75c845d4365addbc9c0262a58a5",
    "run_id": "f2e3f75c845d4365addbc9c0262a58a5",
    "experiment_id": "12728143",
    "user_id": "",
    "status": "FINISHED",
    "start_time": 1654871324827,
    "end_time": 1654871326586,
    "lifecycle_stage": "active",
    "artifact_uri": "dbfs:/databricks/mlflow-tracking/12728143/f2e3f75c845d4365addbc9c0262a58a5/artifacts"
  },
  "params": {
    "max_depth": "1"
  },
  "metrics": {
    "rmse": [
      {
        "value": 0.8520089856588225,
        "timestamp": 1593013216314,
        "step": 0
      }
    ]
  },
  "tags": {
    "mlflow.databricks.cluster.id": "0624-033403-hash220",
    "mlflow.databricks.notebookID": "5014123",
    "mlflow.databricks.notebookPath": "/Users/andre.mesarovic@databricks.com/mlflow/mlflow_galleries/models_basic/python/02b_Sklearn_Train_Predict_Registry",
    "mlflow.databricks.notebookRevisionID": "1654871326670",
    "mlflow.databricks.webappURL": "https://demo.cloud.databricks.com",
    "mlflow.runName": "reg_test",
    "mlflow.source.name": "/Users/andre.mesarovic@databricks.com/mlflow/mlflow_galleries/models_basic/python/02b_Sklearn_Train_Predict_Registry",
    "mlflow.source.type": "NOTEBOOK",
    "mlflow_export_import.metadata.artifact_uri": "dbfs:/databricks/mlflow-tracking/12728143/f2e3f75c845d4365addbc9c0262a58a5/artifacts",
    "mlflow_export_import.metadata.end_time": 1654871326586,
    "mlflow_export_import.metadata.experiment_id": "12728143",
    "mlflow_export_import.metadata.experiment_name": "/Users/andre.mesarovic@databricks.com/experiments/imported/02_Sklearn_Train_Predict",
    "mlflow_export_import.metadata.lifecycle_stage": "active",
    "mlflow_export_import.metadata.run_id": "f2e3f75c845d4365addbc9c0262a58a5",
    "mlflow_export_import.metadata.start_time": 1654871324827,
    "mlflow_export_import.metadata.status": "FINISHED",
    "mlflow_export_import.metadata.timestamp": "1655003687",
    "mlflow_export_import.metadata.timestamp_nice": "2022-06-12 03:14:47",
    "mlflow_export_import.metadata.tracking_uri": "databricks",
    "mlflow_export_import.metadata.user_id": ""
  }
}
